{"name":"Texto en negrita","id":"crear-una-nota-con-texto-enriquecido;texto-en-negrita","testSteps":[{"number":1,"description":"Given Que el usuario ingresa a  bloc de notas online","duration":3812,"startTime":"2023-07-06T14:03:59.672-05:00[America/Bogota]","screenshots":[{"screenshot":"8b6ddce3864013ecc4286b8d51416f22a89ee63ad7ef6e89833ee59d14e14b67.png"}],"result":"SUCCESS","precondition":false,"children":[{"number":2,"description":"Miguel opens the Pagina","duration":3483,"startTime":"2023-07-06T14:03:59.886-05:00[America/Bogota]","screenshots":[{"screenshot":"e7106d600b2ad1cab864e13374cdc7c6a65f99191c1d1546718096d3bf568fb4.png"}],"result":"SUCCESS","precondition":false}]},{"number":3,"description":"When Selecciona Nota de texto enriquecido y diligencia la nota\r\n| strNotaNegrita |\r\n| Prueba nota negrita |","duration":8055,"startTime":"2023-07-06T14:04:03.484-05:00[America/Bogota]","screenshots":[{"screenshot":"1db6e3edc3e86e4588b3c2bf36cb76c57a7ac13ad51a41498a712a378bdfa10d.png"}],"result":"SUCCESS","precondition":false,"children":[{"number":4,"description":"Miguel clicks on Nota enrriquesidas","duration":241,"startTime":"2023-07-06T14:04:03.504-05:00[America/Bogota]","screenshots":[{"screenshot":"8cf99811727e8d771513149863958b10b21c2f0c21d93236c24e52a686ebcab0.png"}],"result":"SUCCESS","precondition":false},{"number":5,"description":"Miguel clicks on Boton negrita","duration":1997,"startTime":"2023-07-06T14:04:03.746-05:00[America/Bogota]","screenshots":[{"screenshot":"caa71b00d8a7df67ea4a3545c80d8b0c604673a74c57a28d9fbb14fc52d124ef.png"}],"result":"SUCCESS","precondition":false},{"number":6,"description":"Miguel enters \u0027Prueba nota negrita\u0027 into BEditor","duration":392,"startTime":"2023-07-06T14:04:05.744-05:00[America/Bogota]","screenshots":[{"screenshot":"723b157d5009da0ba557a654011b7f10c208f4ce1c1770188326e44321ddafce.png"}],"result":"SUCCESS","precondition":false},{"number":7,"description":"Miguel clicks on Boton guardar","duration":255,"startTime":"2023-07-06T14:04:06.137-05:00[America/Bogota]","screenshots":[{"screenshot":"335682f4311370f77a9eaf5b522469034258517fe3ef200e99f0dd5fdc2d53dc.png"}],"result":"SUCCESS","precondition":false}]},{"number":8,"description":"Then Se valida que se crea la nota\r\n| getSrtTextoFinal |\r\n| Note_1, 06-Jul- |","duration":360,"startTime":"2023-07-06T14:04:11.539-05:00[America/Bogota]","screenshots":[{"screenshot":"1db6e3edc3e86e4588b3c2bf36cb76c57a7ac13ad51a41498a712a378bdfa10d.png"}],"result":"SUCCESS","precondition":false,"children":[{"number":9,"description":"Then validacion","duration":179,"startTime":"2023-07-06T14:04:11.583-05:00[America/Bogota]","screenshots":[{"screenshot":"1db6e3edc3e86e4588b3c2bf36cb76c57a7ac13ad51a41498a712a378bdfa10d.png"}],"result":"SUCCESS","precondition":false}]}],"userStory":{"id":"crear-una-nota-con-texto-enriquecido","storyName":"Crear una nota con texto enriquecido","path":"src/test/resources/feature/test.feature","type":"feature"},"featureTag":{"name":"Feature/Crear una nota con texto enriquecido","type":"feature"},"title":"Texto en negrita","tags":[{"name":"Crear","type":"tag"},{"name":"egrita","type":"tag"},{"name":"ota","type":"tag"},{"name":"n","type":"tag"}],"startTime":"2023-07-06T14:03:59.471-05:00[America/Bogota]","duration":12477,"projectKey":"","sessionId":"e9628ae44e31ab2959a9c88fa7398a45","driver":"chrome:miguel","manual":false,"testSource":"Cucumber","result":"SUCCESS"}